xicorrelation/__init__.py
xicorrelation/_version.py
xicorrelation/py.typed
xicorrelation-0.3.0.dist-info/LICENSE
xicorrelation-0.3.0.dist-info/METADATA
xicorrelation-0.3.0.dist-info/WHEEL
xicorrelation-0.3.0.dist-info/top_level.txt
xicorrelation-0.3.0.dist-info/zip-safe
xicorrelation-0.3.0.dist-info/RECORD
