Metadata-Version: 2.1
Name: xicorrelation
Version: 0.3.0
Summary: xicorrelation
Home-page: https://github.com/jettify/xicorrelation
Author: Nikolay Novik
Author-email: nickolainovik@gmail.com
License: Apache 2
Download-URL: https://pypi.org/project/xicorrelation/
Project-URL: Website, https://github.com/jettify/xicorrelation
Project-URL: Documentation, https://xicorrelation.readthedocs.io
Project-URL: Issues, https://github.com/jettify/xicorrelation/issues
Keywords: correlation,statistics
Platform: POSIX
Classifier: License :: OSI Approved :: Apache Software License
Classifier: Intended Audience :: Developers
Classifier: Intended Audience :: Science/Research
Classifier: Programming Language :: Python :: 3
Classifier: Programming Language :: Python :: 3.7
Classifier: Programming Language :: Python :: 3.8
Classifier: Programming Language :: Python :: 3.9
Classifier: Operating System :: OS Independent
Classifier: Development Status :: 3 - Alpha
Classifier: Topic :: Scientific/Engineering
Classifier: Topic :: Software Development :: Libraries
Requires-Python: >=3.6.0
License-File: LICENSE
Requires-Dist: numpy
Requires-Dist: scipy
